CONFIG.md
LICENSE
MANIFEST.in
README.md
config.ini.master
requirements.txt
setup.py
pyamihtml/__init__.py
pyamihtml/ami_bib.py
pyamihtml/ami_config.py
pyamihtml/ami_html.py
pyamihtml/ami_integrate.py
pyamihtml/ami_pdf.py
pyamihtml/ami_svg.py
pyamihtml/ami_util.py
pyamihtml/bbox_copy.py
pyamihtml/file_lib.py
pyamihtml/ipcc.py
pyamihtml/pyamix.py
pyamihtml/util.py
pyamihtml/wikimedia.py
pyamihtml/xml_lib.py
pyamihtml.egg-info/PKG-INFO
pyamihtml.egg-info/SOURCES.txt
pyamihtml.egg-info/dependency_links.txt
pyamihtml.egg-info/entry_points.txt
pyamihtml.egg-info/not-zip-safe
pyamihtml.egg-info/requires.txt
pyamihtml.egg-info/top_level.txt
test/test_all.py
test/test_experiment.py
test/test_file.py
test/test_gui.py
test/test_html.py
test/test_integrate.py
test/test_ipcc.py
test/test_pdf.py
test/test_pyamix.py
test/test_svg.py
test/test_text.py
test/test_util.py
test/test_wikidata.py
test/test_xml.py