Metadata-Version: 2.1
Name: pyamihtml
Version: 0.0.1
Summary: pdf2html converter
Home-page: https://github.com/petermr/pyamihtml
Author: Peter Murray-Rust
Author-email: petermurrayrust@googlemail.com
License: Apache2
Keywords: text and data mining
Platform: UNKNOWN
Classifier: Development Status :: 3 - Alpha
Classifier: Intended Audience :: Developers
Classifier: License :: OSI Approved :: Apache Software License
Classifier: Natural Language :: English
Classifier: Programming Language :: Python :: 3.4
Classifier: Programming Language :: Python :: 3.5
Classifier: Programming Language :: Python :: 3.6
Classifier: Programming Language :: Python :: 3.8
Requires-Python: >=3.7
License-File: LICENSE
